{
  "aggregate": {
    "timestamp": "2021-09-15T11:53:06.174Z",
    "scenariosCreated": 120,
    "scenariosCompleted": 120,
    "requestsCompleted": 120,
    "latency": {
      "min": 100,
      "max": 1009,
      "median": 106,
      "p95": 277,
      "p99": 569.4
    },
    "rps": {
      "count": 120,
      "mean": 0.98
    },
    "scenarioDuration": {
      "min": 2409.2,
      "max": 3360,
      "median": 2443,
      "p95": 2614.3,
      "p99": 2908.7
    },
    "scenarioCounts": {
      "All recipes": 120
    },
    "errors": {},
    "codes": {
      "200": 120
    },
    "matches": 0,
    "customStats": {},
    "counters": {},
    "scenariosAvoided": 0,
    "phases": [
      {
        "duration": 120,
        "arrivalRate": 1,
        "name": "Pipe Clean"
      }
    ]
  },
  "intermediate": [
    {
      "timestamp": "2021-09-15T11:51:13.101Z",
      "scenariosCreated": 9,
      "scenariosCompleted": 7,
      "requestsCompleted": 9,
      "latency": {
        "min": 100,
        "max": 1009,
        "median": 105,
        "p95": 1009,
        "p99": 1009
      },
      "rps": {
        "count": 9,
        "mean": 1
      },
      "scenarioDuration": {
        "min": 2409.2,
        "max": 3360,
        "median": 2442.1,
        "p95": 3360,
        "p99": 3360
      },
      "scenarioCounts": {
        "All recipes": 9
      },
      "errors": {},
      "codes": {
        "200": 9
      },
      "matches": 0,
      "latencies": [
        121000000,
        105000000,
        1009000000,
        104000000,
        100000000,
        190000000,
        104000000,
        103000000,
        381000000
      ],
      "customStats": {},
      "counters": {},
      "concurrency": 2,
      "pendingRequests": 0,
      "scenariosAvoided": 0
    },
    {
      "timestamp": "2021-09-15T11:51:23.085Z",
      "scenariosCreated": 10,
      "scenariosCompleted": 10,
      "requestsCompleted": 10,
      "latency": {
        "min": 100,
        "max": 293,
        "median": 108,
        "p95": 293,
        "p99": 293
      },
      "rps": {
        "count": 10,
        "mean": 1
      },
      "scenarioDuration": {
        "min": 2418.8,
        "max": 2715.3,
        "median": 2442.8,
        "p95": 2715.3,
        "p99": 2715.3
      },
      "scenarioCounts": {
        "All recipes": 10
      },
      "errors": {},
      "codes": {
        "200": 10
      },
      "matches": 0,
      "latencies": [
        102000000,
        279000000,
        101000000,
        293000000,
        108000000,
        166000000,
        100000000,
        103000000,
        276000000,
        108000000
      ],
      "customStats": {},
      "counters": {},
      "concurrency": 2,
      "pendingRequests": 0,
      "scenariosAvoided": 0
    },
    {
      "timestamp": "2021-09-15T11:51:33.104Z",
      "scenariosCreated": 10,
      "scenariosCompleted": 10,
      "requestsCompleted": 10,
      "latency": {
        "min": 101,
        "max": 180,
        "median": 108,
        "p95": 180,
        "p99": 180
      },
      "rps": {
        "count": 10,
        "mean": 1
      },
      "scenarioDuration": {
        "min": 2420.6,
        "max": 2616.4,
        "median": 2455.1,
        "p95": 2616.4,
        "p99": 2616.4
      },
      "scenarioCounts": {
        "All recipes": 10
      },
      "errors": {},
      "codes": {
        "200": 10
      },
      "matches": 0,
      "latencies": [
        105000000,
        180000000,
        106000000,
        106000000,
        171000000,
        107000000,
        101000000,
        179000000,
        109000000,
        166000000
      ],
      "customStats": {},
      "counters": {},
      "concurrency": 2,
      "pendingRequests": 0,
      "scenariosAvoided": 0
    },
    {
      "timestamp": "2021-09-15T11:51:43.095Z",
      "scenariosCreated": 10,
      "scenariosCompleted": 10,
      "requestsCompleted": 10,
      "latency": {
        "min": 100,
        "max": 181,
        "median": 106,
        "p95": 181,
        "p99": 181
      },
      "rps": {
        "count": 10,
        "mean": 1
      },
      "scenarioDuration": {
        "min": 2426.1,
        "max": 2522.2,
        "median": 2449.8,
        "p95": 2522.2,
        "p99": 2522.2
      },
      "scenarioCounts": {
        "All recipes": 10
      },
      "errors": {},
      "codes": {
        "200": 10
      },
      "matches": 0,
      "latencies": [
        106000000,
        106000000,
        106000000,
        103000000,
        181000000,
        104000000,
        178000000,
        100000000,
        166000000,
        104000000
      ],
      "customStats": {},
      "counters": {},
      "concurrency": 2,
      "pendingRequests": 0,
      "scenariosAvoided": 0
    },
    {
      "timestamp": "2021-09-15T11:51:53.096Z",
      "scenariosCreated": 10,
      "scenariosCompleted": 10,
      "requestsCompleted": 10,
      "latency": {
        "min": 101,
        "max": 277,
        "median": 106,
        "p95": 277,
        "p99": 277
      },
      "rps": {
        "count": 10,
        "mean": 1
      },
      "scenarioDuration": {
        "min": 2432.2,
        "max": 2613.2,
        "median": 2443.3,
        "p95": 2613.2,
        "p99": 2613.2
      },
      "scenarioCounts": {
        "All recipes": 10
      },
      "errors": {},
      "codes": {
        "200": 10
      },
      "matches": 0,
      "latencies": [
        165000000,
        107000000,
        269000000,
        105000000,
        104000000,
        104000000,
        277000000,
        107000000,
        101000000,
        104000000
      ],
      "customStats": {},
      "counters": {},
      "concurrency": 2,
      "pendingRequests": 0,
      "scenariosAvoided": 0
    },
    {
      "timestamp": "2021-09-15T11:52:03.108Z",
      "scenariosCreated": 10,
      "scenariosCompleted": 10,
      "requestsCompleted": 10,
      "latency": {
        "min": 100,
        "max": 282,
        "median": 102.5,
        "p95": 282,
        "p99": 282
      },
      "rps": {
        "count": 10,
        "mean": 1
      },
      "scenarioDuration": {
        "min": 2411,
        "max": 2606.3,
        "median": 2430.1,
        "p95": 2606.3,
        "p99": 2606.3
      },
      "scenarioCounts": {
        "All recipes": 10
      },
      "errors": {},
      "codes": {
        "200": 10
      },
      "matches": 0,
      "latencies": [
        169000000,
        101000000,
        282000000,
        101000000,
        178000000,
        102000000,
        104000000,
        100000000,
        103000000,
        100000000
      ],
      "customStats": {},
      "counters": {},
      "concurrency": 2,
      "pendingRequests": 0,
      "scenariosAvoided": 0
    },
    {
      "timestamp": "2021-09-15T11:52:13.093Z",
      "scenariosCreated": 10,
      "scenariosCompleted": 10,
      "requestsCompleted": 10,
      "latency": {
        "min": 101,
        "max": 274,
        "median": 106,
        "p95": 274,
        "p99": 274
      },
      "rps": {
        "count": 10,
        "mean": 1
      },
      "scenarioDuration": {
        "min": 2417.2,
        "max": 2611.6,
        "median": 2439.4,
        "p95": 2611.6,
        "p99": 2611.6
      },
      "scenarioCounts": {
        "All recipes": 10
      },
      "errors": {},
      "codes": {
        "200": 10
      },
      "matches": 0,
      "latencies": [
        138000000,
        104000000,
        156000000,
        103000000,
        104000000,
        274000000,
        104000000,
        101000000,
        182000000,
        108000000
      ],
      "customStats": {},
      "counters": {},
      "concurrency": 2,
      "pendingRequests": 0,
      "scenariosAvoided": 0
    },
    {
      "timestamp": "2021-09-15T11:52:23.100Z",
      "scenariosCreated": 10,
      "scenariosCompleted": 10,
      "requestsCompleted": 10,
      "latency": {
        "min": 100,
        "max": 275,
        "median": 106.5,
        "p95": 275,
        "p99": 275
      },
      "rps": {
        "count": 10,
        "mean": 1
      },
      "scenarioDuration": {
        "min": 2418,
        "max": 2622.5,
        "median": 2453,
        "p95": 2622.5,
        "p99": 2622.5
      },
      "scenarioCounts": {
        "All recipes": 10
      },
      "errors": {},
      "codes": {
        "200": 10
      },
      "matches": 0,
      "latencies": [
        105000000,
        179000000,
        104000000,
        275000000,
        108000000,
        105000000,
        173000000,
        104000000,
        172000000,
        100000000
      ],
      "customStats": {},
      "counters": {},
      "concurrency": 2,
      "pendingRequests": 0,
      "scenariosAvoided": 0
    },
    {
      "timestamp": "2021-09-15T11:52:33.087Z",
      "scenariosCreated": 10,
      "scenariosCompleted": 10,
      "requestsCompleted": 10,
      "latency": {
        "min": 101,
        "max": 251,
        "median": 107.5,
        "p95": 251,
        "p99": 251
      },
      "rps": {
        "count": 10,
        "mean": 1
      },
      "scenarioDuration": {
        "min": 2419.1,
        "max": 2594.6,
        "median": 2488.8,
        "p95": 2594.6,
        "p99": 2594.6
      },
      "scenarioCounts": {
        "All recipes": 10
      },
      "errors": {},
      "codes": {
        "200": 10
      },
      "matches": 0,
      "latencies": [
        251000000,
        109000000,
        102000000,
        184000000,
        105000000,
        177000000,
        101000000,
        180000000,
        105000000,
        106000000
      ],
      "customStats": {},
      "counters": {},
      "concurrency": 2,
      "pendingRequests": 0,
      "scenariosAvoided": 0
    },
    {
      "timestamp": "2021-09-15T11:52:43.104Z",
      "scenariosCreated": 10,
      "scenariosCompleted": 10,
      "requestsCompleted": 10,
      "latency": {
        "min": 100,
        "max": 181,
        "median": 105,
        "p95": 181,
        "p99": 181
      },
      "rps": {
        "count": 10,
        "mean": 1
      },
      "scenarioDuration": {
        "min": 2416.6,
        "max": 2516.6,
        "median": 2442.3,
        "p95": 2516.6,
        "p99": 2516.6
      },
      "scenarioCounts": {
        "All recipes": 10
      },
      "errors": {},
      "codes": {
        "200": 10
      },
      "matches": 0,
      "latencies": [
        169000000,
        106000000,
        104000000,
        101000000,
        176000000,
        100000000,
        101000000,
        181000000,
        101000000,
        163000000
      ],
      "customStats": {},
      "counters": {},
      "concurrency": 2,
      "pendingRequests": 0,
      "scenariosAvoided": 0
    },
    {
      "timestamp": "2021-09-15T11:52:53.103Z",
      "scenariosCreated": 10,
      "scenariosCompleted": 10,
      "requestsCompleted": 10,
      "latency": {
        "min": 100,
        "max": 194,
        "median": 105,
        "p95": 194,
        "p99": 194
      },
      "rps": {
        "count": 10,
        "mean": 1
      },
      "scenarioDuration": {
        "min": 2417.8,
        "max": 2522,
        "median": 2437.5,
        "p95": 2522,
        "p99": 2522
      },
      "scenarioCounts": {
        "All recipes": 10
      },
      "errors": {},
      "codes": {
        "200": 10
      },
      "matches": 0,
      "latencies": [
        105000000,
        104000000,
        102000000,
        184000000,
        105000000,
        182000000,
        105000000,
        100000000,
        194000000,
        101000000
      ],
      "customStats": {},
      "counters": {},
      "concurrency": 2,
      "pendingRequests": 0,
      "scenariosAvoided": 0
    },
    {
      "timestamp": "2021-09-15T11:53:03.089Z",
      "scenariosCreated": 10,
      "scenariosCompleted": 10,
      "requestsCompleted": 10,
      "latency": {
        "min": 100,
        "max": 277,
        "median": 105,
        "p95": 277,
        "p99": 277
      },
      "rps": {
        "count": 10,
        "mean": 1
      },
      "scenarioDuration": {
        "min": 2423.8,
        "max": 2613,
        "median": 2446.9,
        "p95": 2613,
        "p99": 2613
      },
      "scenarioCounts": {
        "All recipes": 10
      },
      "errors": {},
      "codes": {
        "200": 10
      },
      "matches": 0,
      "latencies": [
        152000000,
        102000000,
        277000000,
        103000000,
        175000000,
        107000000,
        106000000,
        104000000,
        102000000,
        100000000
      ],
      "customStats": {},
      "counters": {},
      "concurrency": 2,
      "pendingRequests": 0,
      "scenariosAvoided": 0
    },
    {
      "timestamp": "2021-09-15T11:53:06.166Z",
      "scenariosCreated": 1,
      "scenariosCompleted": 3,
      "requestsCompleted": 1,
      "latency": {
        "min": 274,
        "max": 274,
        "median": 274,
        "p95": 274,
        "p99": 274
      },
      "rps": {
        "count": 1,
        "mean": 0.33
      },
      "scenarioDuration": {
        "min": 2411.8,
        "max": 2615.5,
        "median": 2426.9,
        "p95": 2615.5,
        "p99": 2615.5
      },
      "scenarioCounts": {
        "All recipes": 1
      },
      "errors": {},
      "codes": {
        "200": 1
      },
      "matches": 0,
      "latencies": [
        274000000
      ],
      "customStats": {},
      "counters": {},
      "concurrency": 0,
      "pendingRequests": 0,
      "scenariosAvoided": 0
    }
  ]
}